README.md
setup.cfg
setup.py
pay_ir/__init__.py
pay_ir.egg-info/PKG-INFO
pay_ir.egg-info/SOURCES.txt
pay_ir.egg-info/dependency_links.txt
pay_ir.egg-info/top_level.txt
pay_ir/api/__init__.py
pay_ir/api/client.py
pay_ir/api/helpers.py
pay_ir/api/urls.py
pay_ir/exceptions/__init__.py
pay_ir/exceptions/base.py
pay_ir/exceptions/payment.py
pay_ir/exceptions/verification.py
pay_ir/tests/__init__.py
pay_ir/tests/api_tests.py
pay_ir/utils/__init__.py
pay_ir/utils/reqres.py