Metadata-Version: 1.1
Name: pay-ir
Version: 0.1.2
Summary: Python interface for pay.ir payment gateway.
Home-page: https://github.com/moeenz/pay-ir
Author: Moeen Zamani
Author-email: moeen.zamani@gmail.com
License: MIT
Platform: UNKNOWN
Classifier: Environment :: Console
Classifier: Environment :: Web Environment
Classifier: Operating System :: Microsoft :: Windows
Classifier: Operating System :: Unix
Classifier: Programming Language :: Python
